{
"type": "FeatureCollection",
"crs": { "type": "name", "properties": { "name": "urn:ogc:def:crs:OGC:1.3:CRS84" } },
"features": [
{ "type": "Feature", "properties": { "Polsby_Popper": 0.29287279741877725, "Intra_flows": 48.356262528441185, "Inter_flows": 15.259256772477661, "Dis_EffGap": 49.511887855641184, "White": 567277, "Black": 49586, "Hispanic": 72556, "Asian": 14794, "AmIndian": 3833, "Population": 726218, "Pop": 708046, "White_%": 0.8011866460653686, "Black_%": 0.070032173050903479, "Hispanic_%": 0.10247356810150753, "Asian_%": 0.02089412269824277, "AmIndian_%": 0.0054134900839775948 }, "geometry": { "type": "Point", "coordinates": [ -88.406341366207201, 42.679760714083137 ] } },
{ "type": "Feature", "properties": { "Polsby_Popper": 0.40299212077364394, "Intra_flows": 48.210654784243104, "Inter_flows": 9.9832483945637858, "Dis_EffGap": 49.819333313296859, "White": 596018, "Black": 32236, "Hispanic": 35019, "Asian": 36818, "AmIndian": 3577, "Population": 717485, "Pop": 703668, "White_%": 0.84701592228153044, "Black_%": 0.0458113769561782, "Hispanic_%": 0.049766367093572537, "Asian_%": 0.052322970491766006, "AmIndian_%": 0.0050833631769527671 }, "geometry": { "type": "Point", "coordinates": [ -89.737749395530159, 42.963484758467622 ] } },
{ "type": "Feature", "properties": { "Polsby_Popper": 0.15309762345195568, "Intra_flows": 44.683411162505784, "Inter_flows": 10.654065596171947, "Dis_EffGap": -30.263867288655913, "White": 665754, "Black": 9351, "Hispanic": 15153, "Asian": 17200, "AmIndian": 5531, "Population": 729300, "Pop": 712989, "White_%": 0.93375073107719753, "Black_%": 0.013115209351055908, "Hispanic_%": 0.021252782300989218, "Asian_%": 0.024123794336238007, "AmIndian_%": 0.0077574829345193261 }, "geometry": { "type": "Point", "coordinates": [ -90.891033810445009, 44.050272164022523 ] } },
{ "type": "Feature", "properties": { "Polsby_Popper": 0.27550348449057743, "Intra_flows": 49.81791046568285, "Inter_flows": 19.619132959277017, "Dis_EffGap": 2.3375745275140454, "White": 327815, "Black": 237478, "Hispanic": 112096, "Asian": 36590, "AmIndian": 6234, "Population": 747575, "Pop": 720213, "White_%": 0.45516395844007257, "Black_%": 0.32973300954023321, "Hispanic_%": 0.15564284454737695, "Asian_%": 0.050804414805064611, "AmIndian_%": 0.0086557726672526047 }, "geometry": { "type": "Point", "coordinates": [ -87.968053683367316, 43.076298264921213 ] } },
{ "type": "Feature", "properties": { "Polsby_Popper": 0.40527082626054894, "Intra_flows": 52.027958814183215, "Inter_flows": 20.104397360399904, "Dis_EffGap": 18.065001069041536, "White": 644384, "Black": 12631, "Hispanic": 31147, "Asian": 21564, "AmIndian": 2532, "Population": 729883, "Pop": 712258, "White_%": 0.90470587904944555, "Black_%": 0.017733742548346244, "Hispanic_%": 0.043729940555248238, "Asian_%": 0.030275546220611071, "AmIndian_%": 0.0035548916263488791 }, "geometry": { "type": "Point", "coordinates": [ -88.515533672615263, 43.166029310428989 ] } },
{ "type": "Feature", "properties": { "Polsby_Popper": 0.18630029950635704, "Intra_flows": 44.553757263910043, "Inter_flows": 17.466353717366005, "Dis_EffGap": 38.309267935860419, "White": 644862, "Black": 16659, "Hispanic": 27122, "Asian": 19268, "AmIndian": 3783, "Population": 722898, "Pop": 711694, "White_%": 0.90609447318650993, "Black_%": 0.023407531888704976, "Hispanic_%": 0.038109074967612483, "Asian_%": 0.027073433245186837, "AmIndian_%": 0.0053154867119857693 }, "geometry": { "type": "Point", "coordinates": [ -88.703409208643706, 43.800582520688003 ] } },
{ "type": "Feature", "properties": { "Polsby_Popper": 0.15245579964597317, "Intra_flows": 40.557602983512517, "Inter_flows": 8.0226377294484248, "Dis_EffGap": 28.461028551330145, "White": 664098, "Black": 5595, "Hispanic": 12488, "Asian": 12101, "AmIndian": 15575, "Population": 713757, "Pop": 709857, "White_%": 0.93553772097760535, "Black_%": 0.0078818691651980615, "Hispanic_%": 0.017592275627344663, "Asian_%": 0.01704709540090469, "AmIndian_%": 0.02194103882894724 }, "geometry": { "type": "Point", "coordinates": [ -90.654550132753201, 45.592216967380757 ] } },
{ "type": "Feature", "properties": { "Polsby_Popper": 0.12524620118917715, "Intra_flows": 54.946712246020951, "Inter_flows": 9.8110073229456667, "Dis_EffGap": 22.896078738488505, "White": 627337, "Black": 12720, "Hispanic": 30475, "Asian": 17367, "AmIndian": 19363, "Population": 719859, "Pop": 707262, "White_%": 0.88699378730937051, "Black_%": 0.017984848613385139, "Hispanic_%": 0.043088699802901892, "Asian_%": 0.024555256750680793, "AmIndian_%": 0.027377407523661669 }, "geometry": { "type": "Point", "coordinates": [ -88.28467216648832, 44.831636853530767 ] } }
]
}
