{
"type": "FeatureCollection",
"crs": { "type": "name", "properties": { "name": "urn:ogc:def:crs:OGC:1.3:CRS84" } },
"features": [
{ "type": "Feature", "properties": { "Polsby_Popper": 0.29287279741877725, "Intra_flows": 4835626.2528441185, "Inter_flows": 1525925.6772477662, "Dis_EffGap": 49.511887855641184, "White": 567277, "Black": 49586, "Hispanic": 72556, "Asian": 14794, "AmIndian": 3833, "Population": 726218 }, "geometry": { "type": "Point", "coordinates": [ -88.406341366207201, 42.679760714083137 ] } },
{ "type": "Feature", "properties": { "Polsby_Popper": 0.40299212077364394, "Intra_flows": 4821065.4784243107, "Inter_flows": 998324.8394563786, "Dis_EffGap": 49.819333313296859, "White": 596018, "Black": 32236, "Hispanic": 35019, "Asian": 36818, "AmIndian": 3577, "Population": 717485 }, "geometry": { "type": "Point", "coordinates": [ -89.737749395530159, 42.963484758467622 ] } },
{ "type": "Feature", "properties": { "Polsby_Popper": 0.15309762345195568, "Intra_flows": 4468341.1162505783, "Inter_flows": 1065406.5596171946, "Dis_EffGap": -30.263867288655913, "White": 665754, "Black": 9351, "Hispanic": 15153, "Asian": 17200, "AmIndian": 5531, "Population": 729300 }, "geometry": { "type": "Point", "coordinates": [ -90.891033810445009, 44.050272164022523 ] } },
{ "type": "Feature", "properties": { "Polsby_Popper": 0.27550348449057743, "Intra_flows": 4981791.0465682847, "Inter_flows": 1961913.2959277018, "Dis_EffGap": 2.3375745275140454, "White": 327815, "Black": 237478, "Hispanic": 112096, "Asian": 36590, "AmIndian": 6234, "Population": 747575 }, "geometry": { "type": "Point", "coordinates": [ -87.968053683367316, 43.076298264921213 ] } },
{ "type": "Feature", "properties": { "Polsby_Popper": 0.40527082626054894, "Intra_flows": 5202795.8814183213, "Inter_flows": 2010439.7360399903, "Dis_EffGap": 18.065001069041536, "White": 644384, "Black": 12631, "Hispanic": 31147, "Asian": 21564, "AmIndian": 2532, "Population": 729883 }, "geometry": { "type": "Point", "coordinates": [ -88.515533672615263, 43.166029310428989 ] } },
{ "type": "Feature", "properties": { "Polsby_Popper": 0.18630029950635704, "Intra_flows": 4455375.7263910044, "Inter_flows": 1746635.3717366003, "Dis_EffGap": 38.309267935860419, "White": 644862, "Black": 16659, "Hispanic": 27122, "Asian": 19268, "AmIndian": 3783, "Population": 722898 }, "geometry": { "type": "Point", "coordinates": [ -88.703409208643706, 43.800582520688003 ] } },
{ "type": "Feature", "properties": { "Polsby_Popper": 0.15245579964597317, "Intra_flows": 4055760.2983512515, "Inter_flows": 802263.77294484247, "Dis_EffGap": 28.461028551330145, "White": 664098, "Black": 5595, "Hispanic": 12488, "Asian": 12101, "AmIndian": 15575, "Population": 713757 }, "geometry": { "type": "Point", "coordinates": [ -90.654550132753201, 45.592216967380757 ] } },
{ "type": "Feature", "properties": { "Polsby_Popper": 0.12524620118917715, "Intra_flows": null, "Inter_flows": null, "Dis_EffGap": 22.896078738488505, "White": 627337, "Black": 12720, "Hispanic": 30475, "Asian": 17367, "AmIndian": 19363, "Population": 719859 }, "geometry": { "type": "Point", "coordinates": [ -88.28467216648832, 44.831636853530767 ] } }
]
}
