{
"type": "FeatureCollection",
"crs": { "type": "name", "properties": { "name": "urn:ogc:def:crs:OGC:1.3:CRS84" } },
"features": [
{ "type": "Feature", "properties": { "Polsby_Popper": 0.14709916436676926, "Intra_flows": 4692613.4706097944, "Inter_flows": 1259750.9768577788, "Dis_EffGap": 46.728276612041036, "White": 672031, "Black": 8595, "Hispanic": 19401, "Asian": 20430, "AmIndian": 6110, "Population": 741611 }, "geometry": { "type": "Point", "coordinates": [ -90.178340658557559, 44.476088784568361 ] } },
{ "type": "Feature", "properties": { "Polsby_Popper": 0.13925347863505255, "Intra_flows": 3859145.7318499456, "Inter_flows": 854140.91676264803, "Dis_EffGap": 40.619360768535437, "White": 674258, "Black": 6091, "Hispanic": 11095, "Asian": 8797, "AmIndian": 22427, "Population": 728107 }, "geometry": { "type": "Point", "coordinates": [ -90.654798062920264, 45.643897753175274 ] } },
{ "type": "Feature", "properties": { "Polsby_Popper": 0.067931668521343094, "Intra_flows": 4198274.2639348991, "Inter_flows": 2180995.8574768063, "Dis_EffGap": 36.623390229443864, "White": 667559, "Black": 13173, "Hispanic": 25607, "Asian": 15437, "AmIndian": 3194, "Population": 733890 }, "geometry": { "type": "Point", "coordinates": [ -88.427482532564426, 43.828120116785009 ] } },
{ "type": "Feature", "properties": { "Polsby_Popper": 0.2663419281827451, "Intra_flows": 4432769.023644954, "Inter_flows": 1017650.5649258995, "Dis_EffGap": 35.008325687011137, "White": 596589, "Black": 30170, "Hispanic": 32758, "Asian": 34858, "AmIndian": 3648, "Population": 712041 }, "geometry": { "type": "Point", "coordinates": [ -90.288852665525141, 43.156308418233017 ] } },
{ "type": "Feature", "properties": { "Polsby_Popper": 0.14992786090988061, "Intra_flows": 4594692.6623480711, "Inter_flows": 2069464.8162544412, "Dis_EffGap": -11.770046380332786, "White": 381166, "Black": 162643, "Hispanic": 114104, "Asian": 35203, "AmIndian": 6431, "Population": 718122 }, "geometry": { "type": "Point", "coordinates": [ -87.947163811068876, 43.029117982510343 ] } },
{ "type": "Feature", "properties": { "Polsby_Popper": 0.12733448068835865, "Intra_flows": 4662991.546246714, "Inter_flows": 2478944.5016306345, "Dis_EffGap": 47.280043311870969, "White": 555147, "Black": 89877, "Hispanic": 31771, "Asian": 26200, "AmIndian": 2604, "Population": 728935 }, "geometry": { "type": "Point", "coordinates": [ -88.677387560529212, 43.020320861133008 ] } },
{ "type": "Feature", "properties": { "Polsby_Popper": 0.19273685611013183, "Intra_flows": 4779017.6356595382, "Inter_flows": 1780080.3737738768, "Dis_EffGap": 45.17319440307768, "White": 586859, "Black": 48600, "Hispanic": 69478, "Asian": 12803, "AmIndian": 3540, "Population": 741990 }, "geometry": { "type": "Point", "coordinates": [ -88.53515499097756, 42.671249808104811 ] } },
{ "type": "Feature", "properties": { "Polsby_Popper": 0.098903396495319082, "Intra_flows": 5488591.704828931, "Inter_flows": 1058312.9633099085, "Dis_EffGap": 32.044809714640586, "White": 603936, "Black": 17107, "Hispanic": 31842, "Asian": 21974, "AmIndian": 12474, "Population": 702279 }, "geometry": { "type": "Point", "coordinates": [ -88.186517707596082, 44.509612899416169 ] } }
]
}
