{
"type": "FeatureCollection",
"crs": { "type": "name", "properties": { "name": "urn:ogc:def:crs:OGC:1.3:CRS84" } },
"features": [
{ "type": "Feature", "properties": { "Polsby_Popper": 0.14709916436676926, "Intra_flows": 46.92613470609794, "Inter_flows": 12.597509768577789, "Dis_EffGap": 46.728276612041036, "White": 672031, "Black": 8595, "Hispanic": 19401, "Asian": 20430, "AmIndian": 6110, "Population": 741611, "Pop": 726567, "White_%": 0.92494016381145849, "Black_%": 0.011829604152129122, "Hispanic_%": 0.026702286231001408, "Asian_%": 0.028118535523909013, "AmIndian_%": 0.0084094102815019129 }, "geometry": { "type": "Point", "coordinates": [ -90.178340658557559, 44.476088784568361 ] } },
{ "type": "Feature", "properties": { "Polsby_Popper": 0.13925347863505255, "Intra_flows": 38.591457318499458, "Inter_flows": 8.5414091676264796, "Dis_EffGap": 40.619360768535437, "White": 674258, "Black": 6091, "Hispanic": 11095, "Asian": 8797, "AmIndian": 22427, "Population": 728107, "Pop": 722668, "White_%": 0.93301211621380775, "Black_%": 0.008428489984335822, "Hispanic_%": 0.015352831452340494, "Asian_%": 0.012172948020391107, "AmIndian_%": 0.031033614329124853 }, "geometry": { "type": "Point", "coordinates": [ -90.654798062920264, 45.643897753175274 ] } },
{ "type": "Feature", "properties": { "Polsby_Popper": 0.067931668521343094, "Intra_flows": 41.982742639348992, "Inter_flows": 21.809958574768064, "Dis_EffGap": 36.623390229443864, "White": 667559, "Black": 13173, "Hispanic": 25607, "Asian": 15437, "AmIndian": 3194, "Population": 733890, "Pop": 724970, "White_%": 0.92080913692980404, "Black_%": 0.018170407051326262, "Hispanic_%": 0.03532146157772046, "Asian_%": 0.021293294894961172, "AmIndian_%": 0.0044056995461881181 }, "geometry": { "type": "Point", "coordinates": [ -88.427482532564426, 43.828120116785009 ] } },
{ "type": "Feature", "properties": { "Polsby_Popper": 0.2663419281827451, "Intra_flows": 44.327690236449541, "Inter_flows": 10.176505649258996, "Dis_EffGap": 35.008325687011137, "White": 596589, "Black": 30170, "Hispanic": 32758, "Asian": 34858, "AmIndian": 3648, "Population": 712041, "Pop": 698023, "White_%": 0.854683871448362, "Black_%": 0.043222071479020033, "Hispanic_%": 0.046929685698035739, "Asian_%": 0.049938182552723906, "AmIndian_%": 0.0052261888218583059 }, "geometry": { "type": "Point", "coordinates": [ -90.288852665525141, 43.156308418233017 ] } },
{ "type": "Feature", "properties": { "Polsby_Popper": 0.14992786090988061, "Intra_flows": 45.946926623480714, "Inter_flows": 20.694648162544411, "Dis_EffGap": -11.770046380332786, "White": 381166, "Black": 162643, "Hispanic": 114104, "Asian": 35203, "AmIndian": 6431, "Population": 718122, "Pop": 699547, "White_%": 0.5448754694109188, "Black_%": 0.23249760201959269, "Hispanic_%": 0.16311127057938923, "Asian_%": 0.050322565889068215, "AmIndian_%": 0.0091930921010310966 }, "geometry": { "type": "Point", "coordinates": [ -87.947163811068876, 43.029117982510343 ] } },
{ "type": "Feature", "properties": { "Polsby_Popper": 0.12733448068835865, "Intra_flows": 46.629915462467139, "Inter_flows": 24.789445016306345, "Dis_EffGap": 47.280043311870969, "White": 555147, "Black": 89877, "Hispanic": 31771, "Asian": 26200, "AmIndian": 2604, "Population": 728935, "Pop": 705599, "White_%": 0.78677407422629564, "Black_%": 0.12737688120306292, "Hispanic_%": 0.045026991251404837, "Asian_%": 0.037131571898486253, "AmIndian_%": 0.0036904814207503129 }, "geometry": { "type": "Point", "coordinates": [ -88.677387560529212, 43.020320861133008 ] } },
{ "type": "Feature", "properties": { "Polsby_Popper": 0.19273685611013183, "Intra_flows": 47.790176356595381, "Inter_flows": 17.800803737738768, "Dis_EffGap": 45.17319440307768, "White": 586859, "Black": 48600, "Hispanic": 69478, "Asian": 12803, "AmIndian": 3540, "Population": 741990, "Pop": 721280, "White_%": 0.81363548136645958, "Black_%": 0.06738021295474711, "Hispanic_%": 0.096325976042590952, "Asian_%": 0.017750388198757763, "AmIndian_%": 0.0049079414374445431 }, "geometry": { "type": "Point", "coordinates": [ -88.53515499097756, 42.671249808104811 ] } },
{ "type": "Feature", "properties": { "Polsby_Popper": 0.098903396495319082, "Intra_flows": 54.885917048289308, "Inter_flows": 10.583129633099086, "Dis_EffGap": 32.044809714640586, "White": 603936, "Black": 17107, "Hispanic": 31842, "Asian": 21974, "AmIndian": 12474, "Population": 702279, "Pop": 687333, "White_%": 0.87866579954694446, "Black_%": 0.024888954844304, "Hispanic_%": 0.04632688958627041, "Asian_%": 0.031969947609091956, "AmIndian_%": 0.018148408413389144 }, "geometry": { "type": "Point", "coordinates": [ -88.186517707596082, 44.509612899416169 ] } }
]
}
