{
"type": "FeatureCollection",
"crs": { "type": "name", "properties": { "name": "urn:ogc:def:crs:OGC:1.3:CRS84" } },
"features": [
{ "type": "Feature", "properties": { "Polsby_Popper": 0.20695950689777809, "Intra_flows": 48.000199252015783, "Inter_flows": 15.084121770252979, "Dis_EffGap": -38.643723710497582, "White": 556938, "Black": 50988, "Hispanic": 85864, "Asian": 17241, "AmIndian": 4485, "Population": 735434, "Pop": 715516, "White_%": 0.77837253115234317, "Black_%": 0.0712604609820046, "Hispanic_%": 0.12000290699299526, "Asian_%": 0.024095897226616876, "AmIndian_%": 0.0062682036460400608 }, "geometry": { "type": "Point", "coordinates": [ -88.579120790808602, 42.661721525917777 ] } },
{ "type": "Feature", "properties": { "Polsby_Popper": 0.37747144222124579, "Intra_flows": 47.368191926623744, "Inter_flows": 12.577201156390768, "Dis_EffGap": 21.590430103657319, "White": 592253, "Black": 33999, "Hispanic": 37623, "Asian": 36864, "AmIndian": 3190, "Population": 716454, "Pop": 703929, "White_%": 0.84135331830340843, "Black_%": 0.048298905145263228, "Hispanic_%": 0.053447151630349084, "Asian_%": 0.05236891788802564, "AmIndian_%": 0.0045317070329536071 }, "geometry": { "type": "Point", "coordinates": [ -89.048996595740519, 43.172528970950005 ] } },
{ "type": "Feature", "properties": { "Polsby_Popper": 0.27079642264516779, "Intra_flows": 42.107853835377519, "Inter_flows": 11.895987769818651, "Dis_EffGap": -17.091812963963513, "White": 664671, "Black": 8301, "Hispanic": 16352, "Asian": 14102, "AmIndian": 5475, "Population": 726085, "Pop": 708901, "White_%": 0.93760764902292426, "Black_%": 0.011709674552582096, "Hispanic_%": 0.023066690553405905, "Asian_%": 0.019892763587581342, "AmIndian_%": 0.0077232222835064415 }, "geometry": { "type": "Point", "coordinates": [ -90.741757601699177, 43.706877185125364 ] } },
{ "type": "Feature", "properties": { "Polsby_Popper": 0.45487896086011237, "Intra_flows": 51.198006077854046, "Inter_flows": 18.548198921314, "Dis_EffGap": -2.4165112906313713, "White": 336679, "Black": 237348, "Hispanic": 100864, "Asian": 35440, "AmIndian": 5857, "Population": 743012, "Pop": 716188, "White_%": 0.47009863331974289, "Black_%": 0.3314046032605964, "Hispanic_%": 0.14083452948108596, "Asian_%": 0.04948421364222802, "AmIndian_%": 0.0081780202963467694 }, "geometry": { "type": "Point", "coordinates": [ -87.98177069171193, 43.073421941352748 ] } },
{ "type": "Feature", "properties": { "Polsby_Popper": 0.34531716173735971, "Intra_flows": 52.259379779630827, "Inter_flows": 20.560977127666831, "Dis_EffGap": 16.83139359136203, "White": 648848, "Black": 12703, "Hispanic": 25994, "Asian": 22053, "AmIndian": 2137, "Population": 727270, "Pop": 711735, "White_%": 0.9116426759959817, "Black_%": 0.017847934975798577, "Hispanic_%": 0.036522020133898152, "Asian_%": 0.030984846888237896, "AmIndian_%": 0.0030025220060837252 }, "geometry": { "type": "Point", "coordinates": [ -88.266954647440528, 43.100841617630827 ] } },
{ "type": "Feature", "properties": { "Polsby_Popper": 0.26771609992793088, "Intra_flows": 51.138636480951824, "Inter_flows": 13.303468599181855, "Dis_EffGap": 39.817901635088376, "White": 650587, "Black": 14109, "Hispanic": 24675, "Asian": 18678, "AmIndian": 4737, "Population": 727314, "Pop": 712786, "White_%": 0.91273818509342219, "Black_%": 0.019794159817953776, "Hispanic_%": 0.03461768328783113, "Asian_%": 0.026204218376904148, "AmIndian_%": 0.0066457534238887972 }, "geometry": { "type": "Point", "coordinates": [ -89.336640304235715, 44.085415168522282 ] } },
{ "type": "Feature", "properties": { "Polsby_Popper": 0.20763804202345604, "Intra_flows": 40.080179765981448, "Inter_flows": 8.9663812737228508, "Dis_EffGap": 31.421867899607857, "White": 663989, "Black": 5782, "Hispanic": 12178, "Asian": 12460, "AmIndian": 15427, "Population": 712595, "Pop": 709836, "White_%": 0.93541184160848423, "Black_%": 0.0081455434776483582, "Hispanic_%": 0.017156075487859166, "Asian_%": 0.017553350351348761, "AmIndian_%": 0.021733189074659497 }, "geometry": { "type": "Point", "coordinates": [ -90.744989246151164, 45.649888066229394 ] } },
{ "type": "Feature", "properties": { "Polsby_Popper": 0.11693201639031618, "Intra_flows": 49.826278270249844, "Inter_flows": 11.159308094115701, "Dis_EffGap": 24.828409821330432, "White": 623580, "Black": 13026, "Hispanic": 32506, "Asian": 18864, "AmIndian": 19120, "Population": 718811, "Pop": 707096, "White_%": 0.88188873929424005, "Black_%": 0.018421826739226356, "Hispanic_%": 0.04597112697568647, "Asian_%": 0.02667813139941394, "AmIndian_%": 0.027040175591433128 }, "geometry": { "type": "Point", "coordinates": [ -88.261754922193731, 44.771770130554984 ] } }
]
}
