{
"type": "FeatureCollection",
"crs": { "type": "name", "properties": { "name": "urn:ogc:def:crs:OGC:1.3:CRS84" } },
"features": [
{ "type": "Feature", "properties": { "Polsby_Popper": 0.20695950689777809, "Intra_flows": 4800019.9252015781, "Inter_flows": 1508412.1770252979, "Dis_EffGap": -38.643723710497582, "White": 556938, "Black": 50988, "Hispanic": 85864, "Asian": 17241, "AmIndian": 4485, "Population": 735434 }, "geometry": { "type": "Point", "coordinates": [ -88.579120790808602, 42.661721525917777 ] } },
{ "type": "Feature", "properties": { "Polsby_Popper": 0.37747144222124579, "Intra_flows": 4736819.1926623741, "Inter_flows": 1257720.1156390768, "Dis_EffGap": 21.590430103657319, "White": 592253, "Black": 33999, "Hispanic": 37623, "Asian": 36864, "AmIndian": 3190, "Population": 716454 }, "geometry": { "type": "Point", "coordinates": [ -89.048996595740519, 43.172528970950005 ] } },
{ "type": "Feature", "properties": { "Polsby_Popper": 0.27079642264516779, "Intra_flows": 4210785.3835377516, "Inter_flows": 1189598.7769818651, "Dis_EffGap": -17.091812963963513, "White": 664671, "Black": 8301, "Hispanic": 16352, "Asian": 14102, "AmIndian": 5475, "Population": 726085 }, "geometry": { "type": "Point", "coordinates": [ -90.741757601699177, 43.706877185125364 ] } },
{ "type": "Feature", "properties": { "Polsby_Popper": 0.45487896086011237, "Intra_flows": 5119800.6077854047, "Inter_flows": 1854819.8921314001, "Dis_EffGap": -2.4165112906313713, "White": 336679, "Black": 237348, "Hispanic": 100864, "Asian": 35440, "AmIndian": 5857, "Population": 743012 }, "geometry": { "type": "Point", "coordinates": [ -87.98177069171193, 43.073421941352748 ] } },
{ "type": "Feature", "properties": { "Polsby_Popper": 0.34531716173735971, "Intra_flows": 5225937.9779630825, "Inter_flows": 2056097.712766683, "Dis_EffGap": 16.83139359136203, "White": 648848, "Black": 12703, "Hispanic": 25994, "Asian": 22053, "AmIndian": 2137, "Population": 727270 }, "geometry": { "type": "Point", "coordinates": [ -88.266954647440528, 43.100841617630827 ] } },
{ "type": "Feature", "properties": { "Polsby_Popper": 0.26771609992793088, "Intra_flows": 5113863.6480951821, "Inter_flows": 1330346.8599181855, "Dis_EffGap": 39.817901635088376, "White": 650587, "Black": 14109, "Hispanic": 24675, "Asian": 18678, "AmIndian": 4737, "Population": 727314 }, "geometry": { "type": "Point", "coordinates": [ -89.336640304235715, 44.085415168522282 ] } },
{ "type": "Feature", "properties": { "Polsby_Popper": 0.20763804202345604, "Intra_flows": 4008017.9765981445, "Inter_flows": 896638.127372285, "Dis_EffGap": 31.421867899607857, "White": 663989, "Black": 5782, "Hispanic": 12178, "Asian": 12460, "AmIndian": 15427, "Population": 712595 }, "geometry": { "type": "Point", "coordinates": [ -90.744989246151164, 45.649888066229394 ] } },
{ "type": "Feature", "properties": { "Polsby_Popper": 0.11693201639031618, "Intra_flows": 4982627.8270249842, "Inter_flows": 1115930.8094115702, "Dis_EffGap": 24.828409821330432, "White": 623580, "Black": 13026, "Hispanic": 32506, "Asian": 18864, "AmIndian": 19120, "Population": 718811 }, "geometry": { "type": "Point", "coordinates": [ -88.261754922193731, 44.771770130554984 ] } }
]
}
